xshape/__init__.py
xshape/accessors.py
xshape/cli.py
xshape/xshape.py
xshape-0.1.1.dist-info/DESCRIPTION.rst
xshape-0.1.1.dist-info/METADATA
xshape-0.1.1.dist-info/RECORD
xshape-0.1.1.dist-info/WHEEL
xshape-0.1.1.dist-info/entry_points.txt
xshape-0.1.1.dist-info/metadata.json
xshape-0.1.1.dist-info/top_level.txt
