Metadata-Version: 2.0
Name: xshape
Version: 0.1.1
Summary: Tools for working with shapefiles, topographies, and polygons in xarray
Home-page: https://pypi.python.org/pypi
Author: Michael Delgado
Author-email: delgado.michaelt@gmail.com
License: MIT license
Keywords: xshape
Platform: UNKNOWN
Classifier: Development Status :: 2 - Pre-Alpha
Classifier: Intended Audience :: Developers
Classifier: License :: OSI Approved :: MIT License
Classifier: Natural Language :: English
Classifier: Programming Language :: Python :: 2
Classifier: Programming Language :: Python :: 2.7
Classifier: Programming Language :: Python :: 3
Classifier: Programming Language :: Python :: 3.5
Classifier: Programming Language :: Python :: 3.6
Requires-Dist: Click (>=6.0)
Requires-Dist: pyshp
Requires-Dist: xarray
Requires-Dist: numpy
Requires-Dist: pandas
Requires-Dist: matplotlib
